[
  {
    "video_id": "2907",
    "analysis_json": "/Users/quan/Documents/personal/Stanford application project/artifacts/regression_20260214/new_model/2907_1765738705(Video in Original Quality)_analysis.json",
    "projection": "scale",
    "gate_spacing_m": 8.0,
    "camera_pitch_deg": 0.0,
    "p90_speed_kmh": 1034.087995155447,
    "median_speed_kmh": 181.93424657864486,
    "raw_correction_factor": 18.80159991191722,
    "auto_applied": false,
    "unable_to_calibrate": true,
    "reason": "correction_exceeds_cap",
    "n_dynamic_frames": 497
  },
  {
    "video_id": "2907",
    "analysis_json": "/Users/quan/Documents/personal/Stanford application project/artifacts/regression_20260214/new_model/2907_1765738705(Video in Original Quality)_analysis.json",
    "projection": "scale",
    "gate_spacing_m": 8.0,
    "camera_pitch_deg": 10.0,
    "p90_speed_kmh": 179.56749590599287,
    "median_speed_kmh": 31.592550373587738,
    "raw_correction_factor": 3.264863561927143,
    "auto_applied": true,
    "unable_to_calibrate": false,
    "reason": "",
    "n_dynamic_frames": 497
  },
  {
    "video_id": "2907",
    "analysis_json": "/Users/quan/Documents/personal/Stanford application project/artifacts/regression_20260214/new_model/2907_1765738705(Video in Original Quality)_analysis.json",
    "projection": "scale",
    "gate_spacing_m": 8.0,
    "camera_pitch_deg": 20.0,
    "p90_speed_kmh": 353.6789243144195,
    "median_speed_kmh": 62.22517709067536,
    "raw_correction_factor": 6.4305258966258085,
    "auto_applied": false,
    "unable_to_calibrate": true,
    "reason": "correction_exceeds_cap",
    "n_dynamic_frames": 497
  },
  {
    "video_id": "2907",
    "analysis_json": "/Users/quan/Documents/personal/Stanford application project/artifacts/regression_20260214/new_model/2907_1765738705(Video in Original Quality)_analysis.json",
    "projection": "scale",
    "gate_spacing_m": 8.0,
    "camera_pitch_deg": 30.0,
    "p90_speed_kmh": 517.0439975777233,
    "median_speed_kmh": 90.96712328932243,
    "raw_correction_factor": 9.400799955958606,
    "auto_applied": false,
    "unable_to_calibrate": true,
    "reason": "correction_exceeds_cap",
    "n_dynamic_frames": 497
  },
  {
    "video_id": "2907",
    "analysis_json": "/Users/quan/Documents/personal/Stanford application project/artifacts/regression_20260214/new_model/2907_1765738705(Video in Original Quality)_analysis.json",
    "projection": "scale",
    "gate_spacing_m": 10.0,
    "camera_pitch_deg": 0.0,
    "p90_speed_kmh": 1292.6099939443086,
    "median_speed_kmh": 227.41780822330642,
    "raw_correction_factor": 23.50199988989652,
    "auto_applied": false,
    "unable_to_calibrate": true,
    "reason": "correction_exceeds_cap",
    "n_dynamic_frames": 497
  },
  {
    "video_id": "2907",
    "analysis_json": "/Users/quan/Documents/personal/Stanford application project/artifacts/regression_20260214/new_model/2907_1765738705(Video in Original Quality)_analysis.json",
    "projection": "scale",
    "gate_spacing_m": 10.0,
    "camera_pitch_deg": 10.0,
    "p90_speed_kmh": 224.45936988249107,
    "median_speed_kmh": 39.49068796698446,
    "raw_correction_factor": 4.081079452408929,
    "auto_applied": true,
    "unable_to_calibrate": false,
    "reason": "",
    "n_dynamic_frames": 497
  },
  {
    "video_id": "2907",
    "analysis_json": "/Users/quan/Documents/personal/Stanford application project/artifacts/regression_20260214/new_model/2907_1765738705(Video in Original Quality)_analysis.json",
    "projection": "scale",
    "gate_spacing_m": 10.0,
    "camera_pitch_deg": 20.0,
    "p90_speed_kmh": 442.0986553930242,
    "median_speed_kmh": 77.78147136334474,
    "raw_correction_factor": 8.038157370782258,
    "auto_applied": false,
    "unable_to_calibrate": true,
    "reason": "correction_exceeds_cap",
    "n_dynamic_frames": 497
  },
  {
    "video_id": "2907",
    "analysis_json": "/Users/quan/Documents/personal/Stanford application project/artifacts/regression_20260214/new_model/2907_1765738705(Video in Original Quality)_analysis.json",
    "projection": "scale",
    "gate_spacing_m": 10.0,
    "camera_pitch_deg": 30.0,
    "p90_speed_kmh": 646.3049969721541,
    "median_speed_kmh": 113.70890411165283,
    "raw_correction_factor": 11.750999944948257,
    "auto_applied": false,
    "unable_to_calibrate": true,
    "reason": "correction_exceeds_cap",
    "n_dynamic_frames": 497
  },
  {
    "video_id": "2907",
    "analysis_json": "/Users/quan/Documents/personal/Stanford application project/artifacts/regression_20260214/new_model/2907_1765738705(Video in Original Quality)_analysis.json",
    "projection": "scale",
    "gate_spacing_m": 12.0,
    "camera_pitch_deg": 0.0,
    "p90_speed_kmh": 1551.1319927331708,
    "median_speed_kmh": 272.90136986796654,
    "raw_correction_factor": 28.202399867875833,
    "auto_applied": false,
    "unable_to_calibrate": true,
    "reason": "correction_exceeds_cap",
    "n_dynamic_frames": 497
  },
  {
    "video_id": "2907",
    "analysis_json": "/Users/quan/Documents/personal/Stanford application project/artifacts/regression_20260214/new_model/2907_1765738705(Video in Original Quality)_analysis.json",
    "projection": "scale",
    "gate_spacing_m": 12.0,
    "camera_pitch_deg": 10.0,
    "p90_speed_kmh": 269.3512438589893,
    "median_speed_kmh": 47.38882556038147,
    "raw_correction_factor": 4.897295342890714,
    "auto_applied": true,
    "unable_to_calibrate": false,
    "reason": "",
    "n_dynamic_frames": 497
  },
  {
    "video_id": "2907",
    "analysis_json": "/Users/quan/Documents/personal/Stanford application project/artifacts/regression_20260214/new_model/2907_1765738705(Video in Original Quality)_analysis.json",
    "projection": "scale",
    "gate_spacing_m": 12.0,
    "camera_pitch_deg": 20.0,
    "p90_speed_kmh": 530.5183864716292,
    "median_speed_kmh": 93.3377656360139,
    "raw_correction_factor": 9.645788844938714,
    "auto_applied": false,
    "unable_to_calibrate": true,
    "reason": "correction_exceeds_cap",
    "n_dynamic_frames": 497
  },
  {
    "video_id": "2907",
    "analysis_json": "/Users/quan/Documents/personal/Stanford application project/artifacts/regression_20260214/new_model/2907_1765738705(Video in Original Quality)_analysis.json",
    "projection": "scale",
    "gate_spacing_m": 12.0,
    "camera_pitch_deg": 30.0,
    "p90_speed_kmh": 775.5659963665851,
    "median_speed_kmh": 136.45068493398327,
    "raw_correction_factor": 14.10119993393791,
    "auto_applied": false,
    "unable_to_calibrate": true,
    "reason": "correction_exceeds_cap",
    "n_dynamic_frames": 497
  },
  {
    "video_id": "2907",
    "analysis_json": "/Users/quan/Documents/personal/Stanford application project/artifacts/regression_20260214/new_model/2907_1765738705(Video in Original Quality)_analysis.json",
    "projection": "scale",
    "gate_spacing_m": 14.0,
    "camera_pitch_deg": 0.0,
    "p90_speed_kmh": 1809.6539915220321,
    "median_speed_kmh": 318.3849315126297,
    "raw_correction_factor": 32.90279984585513,
    "auto_applied": false,
    "unable_to_calibrate": true,
    "reason": "correction_exceeds_cap",
    "n_dynamic_frames": 497
  },
  {
    "video_id": "2907",
    "analysis_json": "/Users/quan/Documents/personal/Stanford application project/artifacts/regression_20260214/new_model/2907_1765738705(Video in Original Quality)_analysis.json",
    "projection": "scale",
    "gate_spacing_m": 14.0,
    "camera_pitch_deg": 10.0,
    "p90_speed_kmh": 314.24311783548757,
    "median_speed_kmh": 55.28696315377848,
    "raw_correction_factor": 5.713511233372501,
    "auto_applied": false,
    "unable_to_calibrate": true,
    "reason": "correction_exceeds_cap",
    "n_dynamic_frames": 497
  },
  {
    "video_id": "2907",
    "analysis_json": "/Users/quan/Documents/personal/Stanford application project/artifacts/regression_20260214/new_model/2907_1765738705(Video in Original Quality)_analysis.json",
    "projection": "scale",
    "gate_spacing_m": 14.0,
    "camera_pitch_deg": 20.0,
    "p90_speed_kmh": 618.9381175502339,
    "median_speed_kmh": 108.89405990868231,
    "raw_correction_factor": 11.253420319095161,
    "auto_applied": false,
    "unable_to_calibrate": true,
    "reason": "correction_exceeds_cap",
    "n_dynamic_frames": 497
  },
  {
    "video_id": "2907",
    "analysis_json": "/Users/quan/Documents/personal/Stanford application project/artifacts/regression_20260214/new_model/2907_1765738705(Video in Original Quality)_analysis.json",
    "projection": "scale",
    "gate_spacing_m": 14.0,
    "camera_pitch_deg": 30.0,
    "p90_speed_kmh": 904.8269957610161,
    "median_speed_kmh": 159.1924657563133,
    "raw_correction_factor": 16.451399922927564,
    "auto_applied": false,
    "unable_to_calibrate": true,
    "reason": "correction_exceeds_cap",
    "n_dynamic_frames": 497
  },
  {
    "video_id": "2907",
    "analysis_json": "/Users/quan/Documents/personal/Stanford application project/artifacts/regression_20260214/new_model/2907_1765738705(Video in Original Quality)_analysis.json",
    "projection": "homography",
    "gate_spacing_m": 8.0,
    "camera_pitch_deg": 0.0,
    "p90_speed_kmh": 4037.358063535879,
    "median_speed_kmh": 154.90742917263748,
    "raw_correction_factor": 73.40651024610689,
    "auto_applied": false,
    "unable_to_calibrate": true,
    "reason": "correction_exceeds_cap",
    "n_dynamic_frames": 497
  },
  {
    "video_id": "2907",
    "analysis_json": "/Users/quan/Documents/personal/Stanford application project/artifacts/regression_20260214/new_model/2907_1765738705(Video in Original Quality)_analysis.json",
    "projection": "homography",
    "gate_spacing_m": 8.0,
    "camera_pitch_deg": 10.0,
    "p90_speed_kmh": 4037.358063535879,
    "median_speed_kmh": 154.90742917263748,
    "raw_correction_factor": 73.40651024610689,
    "auto_applied": false,
    "unable_to_calibrate": true,
    "reason": "correction_exceeds_cap",
    "n_dynamic_frames": 497
  },
  {
    "video_id": "2907",
    "analysis_json": "/Users/quan/Documents/personal/Stanford application project/artifacts/regression_20260214/new_model/2907_1765738705(Video in Original Quality)_analysis.json",
    "projection": "homography",
    "gate_spacing_m": 8.0,
    "camera_pitch_deg": 20.0,
    "p90_speed_kmh": 4037.358063535879,
    "median_speed_kmh": 154.90742917263748,
    "raw_correction_factor": 73.40651024610689,
    "auto_applied": false,
    "unable_to_calibrate": true,
    "reason": "correction_exceeds_cap",
    "n_dynamic_frames": 497
  },
  {
    "video_id": "2907",
    "analysis_json": "/Users/quan/Documents/personal/Stanford application project/artifacts/regression_20260214/new_model/2907_1765738705(Video in Original Quality)_analysis.json",
    "projection": "homography",
    "gate_spacing_m": 8.0,
    "camera_pitch_deg": 30.0,
    "p90_speed_kmh": 4037.358063535879,
    "median_speed_kmh": 154.90742917263748,
    "raw_correction_factor": 73.40651024610689,
    "auto_applied": false,
    "unable_to_calibrate": true,
    "reason": "correction_exceeds_cap",
    "n_dynamic_frames": 497
  },
  {
    "video_id": "2907",
    "analysis_json": "/Users/quan/Documents/personal/Stanford application project/artifacts/regression_20260214/new_model/2907_1765738705(Video in Original Quality)_analysis.json",
    "projection": "homography",
    "gate_spacing_m": 10.0,
    "camera_pitch_deg": 0.0,
    "p90_speed_kmh": 4090.7700811835707,
    "median_speed_kmh": 163.48791504947653,
    "raw_correction_factor": 74.37763783970128,
    "auto_applied": false,
    "unable_to_calibrate": true,
    "reason": "correction_exceeds_cap",
    "n_dynamic_frames": 497
  },
  {
    "video_id": "2907",
    "analysis_json": "/Users/quan/Documents/personal/Stanford application project/artifacts/regression_20260214/new_model/2907_1765738705(Video in Original Quality)_analysis.json",
    "projection": "homography",
    "gate_spacing_m": 10.0,
    "camera_pitch_deg": 10.0,
    "p90_speed_kmh": 4090.7700811835707,
    "median_speed_kmh": 163.48791504947653,
    "raw_correction_factor": 74.37763783970128,
    "auto_applied": false,
    "unable_to_calibrate": true,
    "reason": "correction_exceeds_cap",
    "n_dynamic_frames": 497
  },
  {
    "video_id": "2907",
    "analysis_json": "/Users/quan/Documents/personal/Stanford application project/artifacts/regression_20260214/new_model/2907_1765738705(Video in Original Quality)_analysis.json",
    "projection": "homography",
    "gate_spacing_m": 10.0,
    "camera_pitch_deg": 20.0,
    "p90_speed_kmh": 4090.7700811835707,
    "median_speed_kmh": 163.48791504947653,
    "raw_correction_factor": 74.37763783970128,
    "auto_applied": false,
    "unable_to_calibrate": true,
    "reason": "correction_exceeds_cap",
    "n_dynamic_frames": 497
  },
  {
    "video_id": "2907",
    "analysis_json": "/Users/quan/Documents/personal/Stanford application project/artifacts/regression_20260214/new_model/2907_1765738705(Video in Original Quality)_analysis.json",
    "projection": "homography",
    "gate_spacing_m": 10.0,
    "camera_pitch_deg": 30.0,
    "p90_speed_kmh": 4090.7700811835707,
    "median_speed_kmh": 163.48791504947653,
    "raw_correction_factor": 74.37763783970128,
    "auto_applied": false,
    "unable_to_calibrate": true,
    "reason": "correction_exceeds_cap",
    "n_dynamic_frames": 497
  },
  {
    "video_id": "2907",
    "analysis_json": "/Users/quan/Documents/personal/Stanford application project/artifacts/regression_20260214/new_model/2907_1765738705(Video in Original Quality)_analysis.json",
    "projection": "homography",
    "gate_spacing_m": 12.0,
    "camera_pitch_deg": 0.0,
    "p90_speed_kmh": 4065.714861547457,
    "median_speed_kmh": 170.18028499504226,
    "raw_correction_factor": 73.92208839177195,
    "auto_applied": false,
    "unable_to_calibrate": true,
    "reason": "correction_exceeds_cap",
    "n_dynamic_frames": 497
  },
  {
    "video_id": "2907",
    "analysis_json": "/Users/quan/Documents/personal/Stanford application project/artifacts/regression_20260214/new_model/2907_1765738705(Video in Original Quality)_analysis.json",
    "projection": "homography",
    "gate_spacing_m": 12.0,
    "camera_pitch_deg": 10.0,
    "p90_speed_kmh": 4065.714861547457,
    "median_speed_kmh": 170.18028499504226,
    "raw_correction_factor": 73.92208839177195,
    "auto_applied": false,
    "unable_to_calibrate": true,
    "reason": "correction_exceeds_cap",
    "n_dynamic_frames": 497
  },
  {
    "video_id": "2907",
    "analysis_json": "/Users/quan/Documents/personal/Stanford application project/artifacts/regression_20260214/new_model/2907_1765738705(Video in Original Quality)_analysis.json",
    "projection": "homography",
    "gate_spacing_m": 12.0,
    "camera_pitch_deg": 20.0,
    "p90_speed_kmh": 4065.714861547457,
    "median_speed_kmh": 170.18028499504226,
    "raw_correction_factor": 73.92208839177195,
    "auto_applied": false,
    "unable_to_calibrate": true,
    "reason": "correction_exceeds_cap",
    "n_dynamic_frames": 497
  },
  {
    "video_id": "2907",
    "analysis_json": "/Users/quan/Documents/personal/Stanford application project/artifacts/regression_20260214/new_model/2907_1765738705(Video in Original Quality)_analysis.json",
    "projection": "homography",
    "gate_spacing_m": 12.0,
    "camera_pitch_deg": 30.0,
    "p90_speed_kmh": 4065.714861547457,
    "median_speed_kmh": 170.18028499504226,
    "raw_correction_factor": 73.92208839177195,
    "auto_applied": false,
    "unable_to_calibrate": true,
    "reason": "correction_exceeds_cap",
    "n_dynamic_frames": 497
  },
  {
    "video_id": "2907",
    "analysis_json": "/Users/quan/Documents/personal/Stanford application project/artifacts/regression_20260214/new_model/2907_1765738705(Video in Original Quality)_analysis.json",
    "projection": "homography",
    "gate_spacing_m": 14.0,
    "camera_pitch_deg": 0.0,
    "p90_speed_kmh": 4208.340845704145,
    "median_speed_kmh": 176.49679085128335,
    "raw_correction_factor": 76.51528810371173,
    "auto_applied": false,
    "unable_to_calibrate": true,
    "reason": "correction_exceeds_cap",
    "n_dynamic_frames": 497
  },
  {
    "video_id": "2907",
    "analysis_json": "/Users/quan/Documents/personal/Stanford application project/artifacts/regression_20260214/new_model/2907_1765738705(Video in Original Quality)_analysis.json",
    "projection": "homography",
    "gate_spacing_m": 14.0,
    "camera_pitch_deg": 10.0,
    "p90_speed_kmh": 4208.340845704145,
    "median_speed_kmh": 176.49679085128335,
    "raw_correction_factor": 76.51528810371173,
    "auto_applied": false,
    "unable_to_calibrate": true,
    "reason": "correction_exceeds_cap",
    "n_dynamic_frames": 497
  },
  {
    "video_id": "2907",
    "analysis_json": "/Users/quan/Documents/personal/Stanford application project/artifacts/regression_20260214/new_model/2907_1765738705(Video in Original Quality)_analysis.json",
    "projection": "homography",
    "gate_spacing_m": 14.0,
    "camera_pitch_deg": 20.0,
    "p90_speed_kmh": 4208.340845704145,
    "median_speed_kmh": 176.49679085128335,
    "raw_correction_factor": 76.51528810371173,
    "auto_applied": false,
    "unable_to_calibrate": true,
    "reason": "correction_exceeds_cap",
    "n_dynamic_frames": 497
  },
  {
    "video_id": "2907",
    "analysis_json": "/Users/quan/Documents/personal/Stanford application project/artifacts/regression_20260214/new_model/2907_1765738705(Video in Original Quality)_analysis.json",
    "projection": "homography",
    "gate_spacing_m": 14.0,
    "camera_pitch_deg": 30.0,
    "p90_speed_kmh": 4208.340845704145,
    "median_speed_kmh": 176.49679085128335,
    "raw_correction_factor": 76.51528810371173,
    "auto_applied": false,
    "unable_to_calibrate": true,
    "reason": "correction_exceeds_cap",
    "n_dynamic_frames": 497
  },
  {
    "video_id": "2909",
    "analysis_json": "/Users/quan/Documents/personal/Stanford application project/artifacts/regression_20260214/new_model/2909_1765738725(Video in Original Quality)_analysis.json",
    "projection": "scale",
    "gate_spacing_m": 8.0,
    "camera_pitch_deg": 0.0,
    "p90_speed_kmh": 414.5510206586598,
    "median_speed_kmh": 70.61032956792259,
    "raw_correction_factor": 7.537291284702905,
    "auto_applied": false,
    "unable_to_calibrate": true,
    "reason": "correction_exceeds_cap",
    "n_dynamic_frames": 454
  },
  {
    "video_id": "2909",
    "analysis_json": "/Users/quan/Documents/personal/Stanford application project/artifacts/regression_20260214/new_model/2909_1765738725(Video in Original Quality)_analysis.json",
    "projection": "scale",
    "gate_spacing_m": 8.0,
    "camera_pitch_deg": 10.0,
    "p90_speed_kmh": 71.98602928734226,
    "median_speed_kmh": 12.261355053931226,
    "raw_correction_factor": 1.3088368961334957,
    "auto_applied": true,
    "unable_to_calibrate": false,
    "reason": "",
    "n_dynamic_frames": 454
  },
  {
    "video_id": "2909",
    "analysis_json": "/Users/quan/Documents/personal/Stanford application project/artifacts/regression_20260214/new_model/2909_1765738725(Video in Original Quality)_analysis.json",
    "projection": "scale",
    "gate_spacing_m": 8.0,
    "camera_pitch_deg": 20.0,
    "p90_speed_kmh": 141.78479950147707,
    "median_speed_kmh": 24.15015503909371,
    "raw_correction_factor": 2.5779054454814014,
    "auto_applied": true,
    "unable_to_calibrate": false,
    "reason": "",
    "n_dynamic_frames": 454
  },
  {
    "video_id": "2909",
    "analysis_json": "/Users/quan/Documents/personal/Stanford application project/artifacts/regression_20260214/new_model/2909_1765738725(Video in Original Quality)_analysis.json",
    "projection": "scale",
    "gate_spacing_m": 8.0,
    "camera_pitch_deg": 30.0,
    "p90_speed_kmh": 207.27551032932976,
    "median_speed_kmh": 35.30516478396129,
    "raw_correction_factor": 3.76864564235145,
    "auto_applied": true,
    "unable_to_calibrate": false,
    "reason": "",
    "n_dynamic_frames": 454
  },
  {
    "video_id": "2909",
    "analysis_json": "/Users/quan/Documents/personal/Stanford application project/artifacts/regression_20260214/new_model/2909_1765738725(Video in Original Quality)_analysis.json",
    "projection": "scale",
    "gate_spacing_m": 10.0,
    "camera_pitch_deg": 0.0,
    "p90_speed_kmh": 518.1887758233246,
    "median_speed_kmh": 88.2629119599036,
    "raw_correction_factor": 9.421614105878628,
    "auto_applied": false,
    "unable_to_calibrate": true,
    "reason": "correction_exceeds_cap",
    "n_dynamic_frames": 454
  },
  {
    "video_id": "2909",
    "analysis_json": "/Users/quan/Documents/personal/Stanford application project/artifacts/regression_20260214/new_model/2909_1765738725(Video in Original Quality)_analysis.json",
    "projection": "scale",
    "gate_spacing_m": 10.0,
    "camera_pitch_deg": 10.0,
    "p90_speed_kmh": 89.98253660917783,
    "median_speed_kmh": 15.326693817413913,
    "raw_correction_factor": 1.6360461201668697,
    "auto_applied": true,
    "unable_to_calibrate": false,
    "reason": "",
    "n_dynamic_frames": 454
  },
  {
    "video_id": "2909",
    "analysis_json": "/Users/quan/Documents/personal/Stanford application project/artifacts/regression_20260214/new_model/2909_1765738725(Video in Original Quality)_analysis.json",
    "projection": "scale",
    "gate_spacing_m": 10.0,
    "camera_pitch_deg": 20.0,
    "p90_speed_kmh": 177.23099937684634,
    "median_speed_kmh": 30.187693798867333,
    "raw_correction_factor": 3.2223818068517516,
    "auto_applied": true,
    "unable_to_calibrate": false,
    "reason": "",
    "n_dynamic_frames": 454
  },
  {
    "video_id": "2909",
    "analysis_json": "/Users/quan/Documents/personal/Stanford application project/artifacts/regression_20260214/new_model/2909_1765738725(Video in Original Quality)_analysis.json",
    "projection": "scale",
    "gate_spacing_m": 10.0,
    "camera_pitch_deg": 30.0,
    "p90_speed_kmh": 259.09438791166224,
    "median_speed_kmh": 44.1314559799522,
    "raw_correction_factor": 4.710807052939313,
    "auto_applied": true,
    "unable_to_calibrate": false,
    "reason": "",
    "n_dynamic_frames": 454
  },
  {
    "video_id": "2909",
    "analysis_json": "/Users/quan/Documents/personal/Stanford application project/artifacts/regression_20260214/new_model/2909_1765738725(Video in Original Quality)_analysis.json",
    "projection": "scale",
    "gate_spacing_m": 12.0,
    "camera_pitch_deg": 0.0,
    "p90_speed_kmh": 621.8265309879895,
    "median_speed_kmh": 105.91549435188465,
    "raw_correction_factor": 11.305936927054354,
    "auto_applied": false,
    "unable_to_calibrate": true,
    "reason": "correction_exceeds_cap",
    "n_dynamic_frames": 454
  },
  {
    "video_id": "2909",
    "analysis_json": "/Users/quan/Documents/personal/Stanford application project/artifacts/regression_20260214/new_model/2909_1765738725(Video in Original Quality)_analysis.json",
    "projection": "scale",
    "gate_spacing_m": 12.0,
    "camera_pitch_deg": 10.0,
    "p90_speed_kmh": 107.9790439310134,
    "median_speed_kmh": 18.39203258089689,
    "raw_correction_factor": 1.9632553442002436,
    "auto_applied": true,
    "unable_to_calibrate": false,
    "reason": "",
    "n_dynamic_frames": 454
  },
  {
    "video_id": "2909",
    "analysis_json": "/Users/quan/Documents/personal/Stanford application project/artifacts/regression_20260214/new_model/2909_1765738725(Video in Original Quality)_analysis.json",
    "projection": "scale",
    "gate_spacing_m": 12.0,
    "camera_pitch_deg": 20.0,
    "p90_speed_kmh": 212.6771992522155,
    "median_speed_kmh": 36.225232558640954,
    "raw_correction_factor": 3.8668581682221,
    "auto_applied": true,
    "unable_to_calibrate": false,
    "reason": "",
    "n_dynamic_frames": 454
  },
  {
    "video_id": "2909",
    "analysis_json": "/Users/quan/Documents/personal/Stanford application project/artifacts/regression_20260214/new_model/2909_1765738725(Video in Original Quality)_analysis.json",
    "projection": "scale",
    "gate_spacing_m": 12.0,
    "camera_pitch_deg": 30.0,
    "p90_speed_kmh": 310.91326549399486,
    "median_speed_kmh": 52.95774717594232,
    "raw_correction_factor": 5.652968463527179,
    "auto_applied": false,
    "unable_to_calibrate": true,
    "reason": "correction_exceeds_cap",
    "n_dynamic_frames": 454
  },
  {
    "video_id": "2909",
    "analysis_json": "/Users/quan/Documents/personal/Stanford application project/artifacts/regression_20260214/new_model/2909_1765738725(Video in Original Quality)_analysis.json",
    "projection": "scale",
    "gate_spacing_m": 14.0,
    "camera_pitch_deg": 0.0,
    "p90_speed_kmh": 725.4642861526544,
    "median_speed_kmh": 123.56807674386644,
    "raw_correction_factor": 13.19025974823008,
    "auto_applied": false,
    "unable_to_calibrate": true,
    "reason": "correction_exceeds_cap",
    "n_dynamic_frames": 454
  },
  {
    "video_id": "2909",
    "analysis_json": "/Users/quan/Documents/personal/Stanford application project/artifacts/regression_20260214/new_model/2909_1765738725(Video in Original Quality)_analysis.json",
    "projection": "scale",
    "gate_spacing_m": 14.0,
    "camera_pitch_deg": 10.0,
    "p90_speed_kmh": 125.97555125284899,
    "median_speed_kmh": 21.457371344379666,
    "raw_correction_factor": 2.290464568233618,
    "auto_applied": true,
    "unable_to_calibrate": false,
    "reason": "",
    "n_dynamic_frames": 454
  },
  {
    "video_id": "2909",
    "analysis_json": "/Users/quan/Documents/personal/Stanford application project/artifacts/regression_20260214/new_model/2909_1765738725(Video in Original Quality)_analysis.json",
    "projection": "scale",
    "gate_spacing_m": 14.0,
    "camera_pitch_deg": 20.0,
    "p90_speed_kmh": 248.12339912758463,
    "median_speed_kmh": 42.26277131841457,
    "raw_correction_factor": 4.511334529592448,
    "auto_applied": true,
    "unable_to_calibrate": false,
    "reason": "",
    "n_dynamic_frames": 454
  },
  {
    "video_id": "2909",
    "analysis_json": "/Users/quan/Documents/personal/Stanford application project/artifacts/regression_20260214/new_model/2909_1765738725(Video in Original Quality)_analysis.json",
    "projection": "scale",
    "gate_spacing_m": 14.0,
    "camera_pitch_deg": 30.0,
    "p90_speed_kmh": 362.7321430763272,
    "median_speed_kmh": 61.784038371932844,
    "raw_correction_factor": 6.59512987411504,
    "auto_applied": false,
    "unable_to_calibrate": true,
    "reason": "correction_exceeds_cap",
    "n_dynamic_frames": 454
  },
  {
    "video_id": "2909",
    "analysis_json": "/Users/quan/Documents/personal/Stanford application project/artifacts/regression_20260214/new_model/2909_1765738725(Video in Original Quality)_analysis.json",
    "projection": "homography",
    "gate_spacing_m": 8.0,
    "camera_pitch_deg": 0.0,
    "p90_speed_kmh": 4895.618658157025,
    "median_speed_kmh": 306.0976763147631,
    "raw_correction_factor": 89.01124833012771,
    "auto_applied": false,
    "unable_to_calibrate": true,
    "reason": "correction_exceeds_cap",
    "n_dynamic_frames": 454
  },
  {
    "video_id": "2909",
    "analysis_json": "/Users/quan/Documents/personal/Stanford application project/artifacts/regression_20260214/new_model/2909_1765738725(Video in Original Quality)_analysis.json",
    "projection": "homography",
    "gate_spacing_m": 8.0,
    "camera_pitch_deg": 10.0,
    "p90_speed_kmh": 4895.618658157025,
    "median_speed_kmh": 306.0976763147631,
    "raw_correction_factor": 89.01124833012771,
    "auto_applied": false,
    "unable_to_calibrate": true,
    "reason": "correction_exceeds_cap",
    "n_dynamic_frames": 454
  },
  {
    "video_id": "2909",
    "analysis_json": "/Users/quan/Documents/personal/Stanford application project/artifacts/regression_20260214/new_model/2909_1765738725(Video in Original Quality)_analysis.json",
    "projection": "homography",
    "gate_spacing_m": 8.0,
    "camera_pitch_deg": 20.0,
    "p90_speed_kmh": 4895.618658157025,
    "median_speed_kmh": 306.0976763147631,
    "raw_correction_factor": 89.01124833012771,
    "auto_applied": false,
    "unable_to_calibrate": true,
    "reason": "correction_exceeds_cap",
    "n_dynamic_frames": 454
  },
  {
    "video_id": "2909",
    "analysis_json": "/Users/quan/Documents/personal/Stanford application project/artifacts/regression_20260214/new_model/2909_1765738725(Video in Original Quality)_analysis.json",
    "projection": "homography",
    "gate_spacing_m": 8.0,
    "camera_pitch_deg": 30.0,
    "p90_speed_kmh": 4895.618658157025,
    "median_speed_kmh": 306.0976763147631,
    "raw_correction_factor": 89.01124833012771,
    "auto_applied": false,
    "unable_to_calibrate": true,
    "reason": "correction_exceeds_cap",
    "n_dynamic_frames": 454
  },
  {
    "video_id": "2909",
    "analysis_json": "/Users/quan/Documents/personal/Stanford application project/artifacts/regression_20260214/new_model/2909_1765738725(Video in Original Quality)_analysis.json",
    "projection": "homography",
    "gate_spacing_m": 10.0,
    "camera_pitch_deg": 0.0,
    "p90_speed_kmh": 5181.586293474733,
    "median_speed_kmh": 315.9437715378761,
    "raw_correction_factor": 94.21065988135878,
    "auto_applied": false,
    "unable_to_calibrate": true,
    "reason": "correction_exceeds_cap",
    "n_dynamic_frames": 454
  },
  {
    "video_id": "2909",
    "analysis_json": "/Users/quan/Documents/personal/Stanford application project/artifacts/regression_20260214/new_model/2909_1765738725(Video in Original Quality)_analysis.json",
    "projection": "homography",
    "gate_spacing_m": 10.0,
    "camera_pitch_deg": 10.0,
    "p90_speed_kmh": 5181.586293474733,
    "median_speed_kmh": 315.9437715378761,
    "raw_correction_factor": 94.21065988135878,
    "auto_applied": false,
    "unable_to_calibrate": true,
    "reason": "correction_exceeds_cap",
    "n_dynamic_frames": 454
  },
  {
    "video_id": "2909",
    "analysis_json": "/Users/quan/Documents/personal/Stanford application project/artifacts/regression_20260214/new_model/2909_1765738725(Video in Original Quality)_analysis.json",
    "projection": "homography",
    "gate_spacing_m": 10.0,
    "camera_pitch_deg": 20.0,
    "p90_speed_kmh": 5181.586293474733,
    "median_speed_kmh": 315.9437715378761,
    "raw_correction_factor": 94.21065988135878,
    "auto_applied": false,
    "unable_to_calibrate": true,
    "reason": "correction_exceeds_cap",
    "n_dynamic_frames": 454
  },
  {
    "video_id": "2909",
    "analysis_json": "/Users/quan/Documents/personal/Stanford application project/artifacts/regression_20260214/new_model/2909_1765738725(Video in Original Quality)_analysis.json",
    "projection": "homography",
    "gate_spacing_m": 10.0,
    "camera_pitch_deg": 30.0,
    "p90_speed_kmh": 5181.586293474733,
    "median_speed_kmh": 315.9437715378761,
    "raw_correction_factor": 94.21065988135878,
    "auto_applied": false,
    "unable_to_calibrate": true,
    "reason": "correction_exceeds_cap",
    "n_dynamic_frames": 454
  },
  {
    "video_id": "2909",
    "analysis_json": "/Users/quan/Documents/personal/Stanford application project/artifacts/regression_20260214/new_model/2909_1765738725(Video in Original Quality)_analysis.json",
    "projection": "homography",
    "gate_spacing_m": 12.0,
    "camera_pitch_deg": 0.0,
    "p90_speed_kmh": 5432.224965049783,
    "median_speed_kmh": 337.304982489646,
    "raw_correction_factor": 98.7677266372688,
    "auto_applied": false,
    "unable_to_calibrate": true,
    "reason": "correction_exceeds_cap",
    "n_dynamic_frames": 454
  },
  {
    "video_id": "2909",
    "analysis_json": "/Users/quan/Documents/personal/Stanford application project/artifacts/regression_20260214/new_model/2909_1765738725(Video in Original Quality)_analysis.json",
    "projection": "homography",
    "gate_spacing_m": 12.0,
    "camera_pitch_deg": 10.0,
    "p90_speed_kmh": 5432.224965049783,
    "median_speed_kmh": 337.304982489646,
    "raw_correction_factor": 98.7677266372688,
    "auto_applied": false,
    "unable_to_calibrate": true,
    "reason": "correction_exceeds_cap",
    "n_dynamic_frames": 454
  },
  {
    "video_id": "2909",
    "analysis_json": "/Users/quan/Documents/personal/Stanford application project/artifacts/regression_20260214/new_model/2909_1765738725(Video in Original Quality)_analysis.json",
    "projection": "homography",
    "gate_spacing_m": 12.0,
    "camera_pitch_deg": 20.0,
    "p90_speed_kmh": 5432.224965049783,
    "median_speed_kmh": 337.304982489646,
    "raw_correction_factor": 98.7677266372688,
    "auto_applied": false,
    "unable_to_calibrate": true,
    "reason": "correction_exceeds_cap",
    "n_dynamic_frames": 454
  },
  {
    "video_id": "2909",
    "analysis_json": "/Users/quan/Documents/personal/Stanford application project/artifacts/regression_20260214/new_model/2909_1765738725(Video in Original Quality)_analysis.json",
    "projection": "homography",
    "gate_spacing_m": 12.0,
    "camera_pitch_deg": 30.0,
    "p90_speed_kmh": 5432.224965049783,
    "median_speed_kmh": 337.304982489646,
    "raw_correction_factor": 98.7677266372688,
    "auto_applied": false,
    "unable_to_calibrate": true,
    "reason": "correction_exceeds_cap",
    "n_dynamic_frames": 454
  },
  {
    "video_id": "2909",
    "analysis_json": "/Users/quan/Documents/personal/Stanford application project/artifacts/regression_20260214/new_model/2909_1765738725(Video in Original Quality)_analysis.json",
    "projection": "homography",
    "gate_spacing_m": 14.0,
    "camera_pitch_deg": 0.0,
    "p90_speed_kmh": 5575.813958718626,
    "median_speed_kmh": 353.2104134287851,
    "raw_correction_factor": 101.37843561306593,
    "auto_applied": false,
    "unable_to_calibrate": true,
    "reason": "correction_exceeds_cap",
    "n_dynamic_frames": 454
  },
  {
    "video_id": "2909",
    "analysis_json": "/Users/quan/Documents/personal/Stanford application project/artifacts/regression_20260214/new_model/2909_1765738725(Video in Original Quality)_analysis.json",
    "projection": "homography",
    "gate_spacing_m": 14.0,
    "camera_pitch_deg": 10.0,
    "p90_speed_kmh": 5575.813958718626,
    "median_speed_kmh": 353.2104134287851,
    "raw_correction_factor": 101.37843561306593,
    "auto_applied": false,
    "unable_to_calibrate": true,
    "reason": "correction_exceeds_cap",
    "n_dynamic_frames": 454
  },
  {
    "video_id": "2909",
    "analysis_json": "/Users/quan/Documents/personal/Stanford application project/artifacts/regression_20260214/new_model/2909_1765738725(Video in Original Quality)_analysis.json",
    "projection": "homography",
    "gate_spacing_m": 14.0,
    "camera_pitch_deg": 20.0,
    "p90_speed_kmh": 5575.813958718626,
    "median_speed_kmh": 353.2104134287851,
    "raw_correction_factor": 101.37843561306593,
    "auto_applied": false,
    "unable_to_calibrate": true,
    "reason": "correction_exceeds_cap",
    "n_dynamic_frames": 454
  },
  {
    "video_id": "2909",
    "analysis_json": "/Users/quan/Documents/personal/Stanford application project/artifacts/regression_20260214/new_model/2909_1765738725(Video in Original Quality)_analysis.json",
    "projection": "homography",
    "gate_spacing_m": 14.0,
    "camera_pitch_deg": 30.0,
    "p90_speed_kmh": 5575.813958718626,
    "median_speed_kmh": 353.2104134287851,
    "raw_correction_factor": 101.37843561306593,
    "auto_applied": false,
    "unable_to_calibrate": true,
    "reason": "correction_exceeds_cap",
    "n_dynamic_frames": 454
  },
  {
    "video_id": "2911",
    "analysis_json": "/Users/quan/Documents/personal/Stanford application project/artifacts/regression_20260214/new_model/2911_1765738746(Video in Original Quality)_analysis.json",
    "projection": "scale",
    "gate_spacing_m": 8.0,
    "camera_pitch_deg": 0.0,
    "p90_speed_kmh": 22331.416385024786,
    "median_speed_kmh": 2709.8926698883415,
    "raw_correction_factor": 406.0257524549961,
    "auto_applied": false,
    "unable_to_calibrate": true,
    "reason": "correction_exceeds_cap",
    "n_dynamic_frames": 463
  },
  {
    "video_id": "2911",
    "analysis_json": "/Users/quan/Documents/personal/Stanford application project/artifacts/regression_20260214/new_model/2911_1765738746(Video in Original Quality)_analysis.json",
    "projection": "scale",
    "gate_spacing_m": 8.0,
    "camera_pitch_deg": 10.0,
    "p90_speed_kmh": 3877.8097599809817,
    "median_speed_kmh": 470.5679237990942,
    "raw_correction_factor": 70.50563199965421,
    "auto_applied": false,
    "unable_to_calibrate": true,
    "reason": "correction_exceeds_cap",
    "n_dynamic_frames": 463
  },
  {
    "video_id": "2911",
    "analysis_json": "/Users/quan/Documents/personal/Stanford application project/artifacts/regression_20260214/new_model/2911_1765738746(Video in Original Quality)_analysis.json",
    "projection": "scale",
    "gate_spacing_m": 8.0,
    "camera_pitch_deg": 20.0,
    "p90_speed_kmh": 7637.794232671365,
    "median_speed_kmh": 926.8378793524619,
    "raw_correction_factor": 138.86898604857026,
    "auto_applied": false,
    "unable_to_calibrate": true,
    "reason": "correction_exceeds_cap",
    "n_dynamic_frames": 463
  },
  {
    "video_id": "2911",
    "analysis_json": "/Users/quan/Documents/personal/Stanford application project/artifacts/regression_20260214/new_model/2911_1765738746(Video in Original Quality)_analysis.json",
    "projection": "scale",
    "gate_spacing_m": 8.0,
    "camera_pitch_deg": 30.0,
    "p90_speed_kmh": 11165.708192512395,
    "median_speed_kmh": 1354.9463349441708,
    "raw_correction_factor": 203.01287622749808,
    "auto_applied": false,
    "unable_to_calibrate": true,
    "reason": "correction_exceeds_cap",
    "n_dynamic_frames": 463
  },
  {
    "video_id": "2911",
    "analysis_json": "/Users/quan/Documents/personal/Stanford application project/artifacts/regression_20260214/new_model/2911_1765738746(Video in Original Quality)_analysis.json",
    "projection": "scale",
    "gate_spacing_m": 10.0,
    "camera_pitch_deg": 0.0,
    "p90_speed_kmh": 27914.270481280986,
    "median_speed_kmh": 3387.3658373605235,
    "raw_correction_factor": 507.5321905687452,
    "auto_applied": false,
    "unable_to_calibrate": true,
    "reason": "correction_exceeds_cap",
    "n_dynamic_frames": 463
  },
  {
    "video_id": "2911",
    "analysis_json": "/Users/quan/Documents/personal/Stanford application project/artifacts/regression_20260214/new_model/2911_1765738746(Video in Original Quality)_analysis.json",
    "projection": "scale",
    "gate_spacing_m": 10.0,
    "camera_pitch_deg": 10.0,
    "p90_speed_kmh": 4847.2621999762305,
    "median_speed_kmh": 588.2099047488676,
    "raw_correction_factor": 88.13203999956782,
    "auto_applied": false,
    "unable_to_calibrate": true,
    "reason": "correction_exceeds_cap",
    "n_dynamic_frames": 463
  },
  {
    "video_id": "2911",
    "analysis_json": "/Users/quan/Documents/personal/Stanford application project/artifacts/regression_20260214/new_model/2911_1765738746(Video in Original Quality)_analysis.json",
    "projection": "scale",
    "gate_spacing_m": 10.0,
    "camera_pitch_deg": 20.0,
    "p90_speed_kmh": 9547.242790839206,
    "median_speed_kmh": 1158.5473491905777,
    "raw_correction_factor": 173.58623256071283,
    "auto_applied": false,
    "unable_to_calibrate": true,
    "reason": "correction_exceeds_cap",
    "n_dynamic_frames": 463
  },
  {
    "video_id": "2911",
    "analysis_json": "/Users/quan/Documents/personal/Stanford application project/artifacts/regression_20260214/new_model/2911_1765738746(Video in Original Quality)_analysis.json",
    "projection": "scale",
    "gate_spacing_m": 10.0,
    "camera_pitch_deg": 30.0,
    "p90_speed_kmh": 13957.135240640497,
    "median_speed_kmh": 1693.6829186802618,
    "raw_correction_factor": 253.76609528437265,
    "auto_applied": false,
    "unable_to_calibrate": true,
    "reason": "correction_exceeds_cap",
    "n_dynamic_frames": 463
  },
  {
    "video_id": "2911",
    "analysis_json": "/Users/quan/Documents/personal/Stanford application project/artifacts/regression_20260214/new_model/2911_1765738746(Video in Original Quality)_analysis.json",
    "projection": "scale",
    "gate_spacing_m": 12.0,
    "camera_pitch_deg": 0.0,
    "p90_speed_kmh": 33497.12457753719,
    "median_speed_kmh": 4064.8390048327074,
    "raw_correction_factor": 609.0386286824944,
    "auto_applied": false,
    "unable_to_calibrate": true,
    "reason": "correction_exceeds_cap",
    "n_dynamic_frames": 463
  },
  {
    "video_id": "2911",
    "analysis_json": "/Users/quan/Documents/personal/Stanford application project/artifacts/regression_20260214/new_model/2911_1765738746(Video in Original Quality)_analysis.json",
    "projection": "scale",
    "gate_spacing_m": 12.0,
    "camera_pitch_deg": 10.0,
    "p90_speed_kmh": 5816.7146399714775,
    "median_speed_kmh": 705.851885698641,
    "raw_correction_factor": 105.7584479994814,
    "auto_applied": false,
    "unable_to_calibrate": true,
    "reason": "correction_exceeds_cap",
    "n_dynamic_frames": 463
  },
  {
    "video_id": "2911",
    "analysis_json": "/Users/quan/Documents/personal/Stanford application project/artifacts/regression_20260214/new_model/2911_1765738746(Video in Original Quality)_analysis.json",
    "projection": "scale",
    "gate_spacing_m": 12.0,
    "camera_pitch_deg": 20.0,
    "p90_speed_kmh": 11456.691349007051,
    "median_speed_kmh": 1390.256819028693,
    "raw_correction_factor": 208.30347907285548,
    "auto_applied": false,
    "unable_to_calibrate": true,
    "reason": "correction_exceeds_cap",
    "n_dynamic_frames": 463
  },
  {
    "video_id": "2911",
    "analysis_json": "/Users/quan/Documents/personal/Stanford application project/artifacts/regression_20260214/new_model/2911_1765738746(Video in Original Quality)_analysis.json",
    "projection": "scale",
    "gate_spacing_m": 12.0,
    "camera_pitch_deg": 30.0,
    "p90_speed_kmh": 16748.562288768597,
    "median_speed_kmh": 2032.4195024163537,
    "raw_correction_factor": 304.5193143412472,
    "auto_applied": false,
    "unable_to_calibrate": true,
    "reason": "correction_exceeds_cap",
    "n_dynamic_frames": 463
  },
  {
    "video_id": "2911",
    "analysis_json": "/Users/quan/Documents/personal/Stanford application project/artifacts/regression_20260214/new_model/2911_1765738746(Video in Original Quality)_analysis.json",
    "projection": "scale",
    "gate_spacing_m": 14.0,
    "camera_pitch_deg": 0.0,
    "p90_speed_kmh": 39079.9786737934,
    "median_speed_kmh": 4742.312172304891,
    "raw_correction_factor": 710.5450667962435,
    "auto_applied": false,
    "unable_to_calibrate": true,
    "reason": "correction_exceeds_cap",
    "n_dynamic_frames": 463
  },
  {
    "video_id": "2911",
    "analysis_json": "/Users/quan/Documents/personal/Stanford application project/artifacts/regression_20260214/new_model/2911_1765738746(Video in Original Quality)_analysis.json",
    "projection": "scale",
    "gate_spacing_m": 14.0,
    "camera_pitch_deg": 10.0,
    "p90_speed_kmh": 6786.167079966724,
    "median_speed_kmh": 823.4938666484147,
    "raw_correction_factor": 123.38485599939497,
    "auto_applied": false,
    "unable_to_calibrate": true,
    "reason": "correction_exceeds_cap",
    "n_dynamic_frames": 463
  },
  {
    "video_id": "2911",
    "analysis_json": "/Users/quan/Documents/personal/Stanford application project/artifacts/regression_20260214/new_model/2911_1765738746(Video in Original Quality)_analysis.json",
    "projection": "scale",
    "gate_spacing_m": 14.0,
    "camera_pitch_deg": 20.0,
    "p90_speed_kmh": 13366.139907174886,
    "median_speed_kmh": 1621.9662888667112,
    "raw_correction_factor": 243.02072558499793,
    "auto_applied": false,
    "unable_to_calibrate": true,
    "reason": "correction_exceeds_cap",
    "n_dynamic_frames": 463
  },
  {
    "video_id": "2911",
    "analysis_json": "/Users/quan/Documents/personal/Stanford application project/artifacts/regression_20260214/new_model/2911_1765738746(Video in Original Quality)_analysis.json",
    "projection": "scale",
    "gate_spacing_m": 14.0,
    "camera_pitch_deg": 30.0,
    "p90_speed_kmh": 19539.989336896702,
    "median_speed_kmh": 2371.1560861524454,
    "raw_correction_factor": 355.2725333981219,
    "auto_applied": false,
    "unable_to_calibrate": true,
    "reason": "correction_exceeds_cap",
    "n_dynamic_frames": 463
  },
  {
    "video_id": "2911",
    "analysis_json": "/Users/quan/Documents/personal/Stanford application project/artifacts/regression_20260214/new_model/2911_1765738746(Video in Original Quality)_analysis.json",
    "projection": "homography",
    "gate_spacing_m": 8.0,
    "camera_pitch_deg": 0.0,
    "p90_speed_kmh": 148761.19219258294,
    "median_speed_kmh": 1585.603445571228,
    "raw_correction_factor": 2704.7489489560535,
    "auto_applied": false,
    "unable_to_calibrate": true,
    "reason": "correction_exceeds_cap",
    "n_dynamic_frames": 463
  },
  {
    "video_id": "2911",
    "analysis_json": "/Users/quan/Documents/personal/Stanford application project/artifacts/regression_20260214/new_model/2911_1765738746(Video in Original Quality)_analysis.json",
    "projection": "homography",
    "gate_spacing_m": 8.0,
    "camera_pitch_deg": 10.0,
    "p90_speed_kmh": 148761.19219258294,
    "median_speed_kmh": 1585.603445571228,
    "raw_correction_factor": 2704.7489489560535,
    "auto_applied": false,
    "unable_to_calibrate": true,
    "reason": "correction_exceeds_cap",
    "n_dynamic_frames": 463
  },
  {
    "video_id": "2911",
    "analysis_json": "/Users/quan/Documents/personal/Stanford application project/artifacts/regression_20260214/new_model/2911_1765738746(Video in Original Quality)_analysis.json",
    "projection": "homography",
    "gate_spacing_m": 8.0,
    "camera_pitch_deg": 20.0,
    "p90_speed_kmh": 148761.19219258294,
    "median_speed_kmh": 1585.603445571228,
    "raw_correction_factor": 2704.7489489560535,
    "auto_applied": false,
    "unable_to_calibrate": true,
    "reason": "correction_exceeds_cap",
    "n_dynamic_frames": 463
  },
  {
    "video_id": "2911",
    "analysis_json": "/Users/quan/Documents/personal/Stanford application project/artifacts/regression_20260214/new_model/2911_1765738746(Video in Original Quality)_analysis.json",
    "projection": "homography",
    "gate_spacing_m": 8.0,
    "camera_pitch_deg": 30.0,
    "p90_speed_kmh": 148761.19219258294,
    "median_speed_kmh": 1585.603445571228,
    "raw_correction_factor": 2704.7489489560535,
    "auto_applied": false,
    "unable_to_calibrate": true,
    "reason": "correction_exceeds_cap",
    "n_dynamic_frames": 463
  },
  {
    "video_id": "2911",
    "analysis_json": "/Users/quan/Documents/personal/Stanford application project/artifacts/regression_20260214/new_model/2911_1765738746(Video in Original Quality)_analysis.json",
    "projection": "homography",
    "gate_spacing_m": 10.0,
    "camera_pitch_deg": 0.0,
    "p90_speed_kmh": 156304.11561899824,
    "median_speed_kmh": 1526.3417405678517,
    "raw_correction_factor": 2841.8930112545136,
    "auto_applied": false,
    "unable_to_calibrate": true,
    "reason": "correction_exceeds_cap",
    "n_dynamic_frames": 463
  },
  {
    "video_id": "2911",
    "analysis_json": "/Users/quan/Documents/personal/Stanford application project/artifacts/regression_20260214/new_model/2911_1765738746(Video in Original Quality)_analysis.json",
    "projection": "homography",
    "gate_spacing_m": 10.0,
    "camera_pitch_deg": 10.0,
    "p90_speed_kmh": 156304.11561899824,
    "median_speed_kmh": 1526.3417405678517,
    "raw_correction_factor": 2841.8930112545136,
    "auto_applied": false,
    "unable_to_calibrate": true,
    "reason": "correction_exceeds_cap",
    "n_dynamic_frames": 463
  },
  {
    "video_id": "2911",
    "analysis_json": "/Users/quan/Documents/personal/Stanford application project/artifacts/regression_20260214/new_model/2911_1765738746(Video in Original Quality)_analysis.json",
    "projection": "homography",
    "gate_spacing_m": 10.0,
    "camera_pitch_deg": 20.0,
    "p90_speed_kmh": 156304.11561899824,
    "median_speed_kmh": 1526.3417405678517,
    "raw_correction_factor": 2841.8930112545136,
    "auto_applied": false,
    "unable_to_calibrate": true,
    "reason": "correction_exceeds_cap",
    "n_dynamic_frames": 463
  },
  {
    "video_id": "2911",
    "analysis_json": "/Users/quan/Documents/personal/Stanford application project/artifacts/regression_20260214/new_model/2911_1765738746(Video in Original Quality)_analysis.json",
    "projection": "homography",
    "gate_spacing_m": 10.0,
    "camera_pitch_deg": 30.0,
    "p90_speed_kmh": 156304.11561899824,
    "median_speed_kmh": 1526.3417405678517,
    "raw_correction_factor": 2841.8930112545136,
    "auto_applied": false,
    "unable_to_calibrate": true,
    "reason": "correction_exceeds_cap",
    "n_dynamic_frames": 463
  },
  {
    "video_id": "2911",
    "analysis_json": "/Users/quan/Documents/personal/Stanford application project/artifacts/regression_20260214/new_model/2911_1765738746(Video in Original Quality)_analysis.json",
    "projection": "homography",
    "gate_spacing_m": 12.0,
    "camera_pitch_deg": 0.0,
    "p90_speed_kmh": 162149.65027502834,
    "median_speed_kmh": 1629.828667707969,
    "raw_correction_factor": 2948.1754595459697,
    "auto_applied": false,
    "unable_to_calibrate": true,
    "reason": "correction_exceeds_cap",
    "n_dynamic_frames": 463
  },
  {
    "video_id": "2911",
    "analysis_json": "/Users/quan/Documents/personal/Stanford application project/artifacts/regression_20260214/new_model/2911_1765738746(Video in Original Quality)_analysis.json",
    "projection": "homography",
    "gate_spacing_m": 12.0,
    "camera_pitch_deg": 10.0,
    "p90_speed_kmh": 162149.65027502834,
    "median_speed_kmh": 1629.828667707969,
    "raw_correction_factor": 2948.1754595459697,
    "auto_applied": false,
    "unable_to_calibrate": true,
    "reason": "correction_exceeds_cap",
    "n_dynamic_frames": 463
  },
  {
    "video_id": "2911",
    "analysis_json": "/Users/quan/Documents/personal/Stanford application project/artifacts/regression_20260214/new_model/2911_1765738746(Video in Original Quality)_analysis.json",
    "projection": "homography",
    "gate_spacing_m": 12.0,
    "camera_pitch_deg": 20.0,
    "p90_speed_kmh": 162149.65027502834,
    "median_speed_kmh": 1629.828667707969,
    "raw_correction_factor": 2948.1754595459697,
    "auto_applied": false,
    "unable_to_calibrate": true,
    "reason": "correction_exceeds_cap",
    "n_dynamic_frames": 463
  },
  {
    "video_id": "2911",
    "analysis_json": "/Users/quan/Documents/personal/Stanford application project/artifacts/regression_20260214/new_model/2911_1765738746(Video in Original Quality)_analysis.json",
    "projection": "homography",
    "gate_spacing_m": 12.0,
    "camera_pitch_deg": 30.0,
    "p90_speed_kmh": 162149.65027502834,
    "median_speed_kmh": 1629.828667707969,
    "raw_correction_factor": 2948.1754595459697,
    "auto_applied": false,
    "unable_to_calibrate": true,
    "reason": "correction_exceeds_cap",
    "n_dynamic_frames": 463
  },
  {
    "video_id": "2911",
    "analysis_json": "/Users/quan/Documents/personal/Stanford application project/artifacts/regression_20260214/new_model/2911_1765738746(Video in Original Quality)_analysis.json",
    "projection": "homography",
    "gate_spacing_m": 14.0,
    "camera_pitch_deg": 0.0,
    "p90_speed_kmh": 166155.11737779187,
    "median_speed_kmh": 1710.647076567101,
    "raw_correction_factor": 3021.0021341416705,
    "auto_applied": false,
    "unable_to_calibrate": true,
    "reason": "correction_exceeds_cap",
    "n_dynamic_frames": 463
  },
  {
    "video_id": "2911",
    "analysis_json": "/Users/quan/Documents/personal/Stanford application project/artifacts/regression_20260214/new_model/2911_1765738746(Video in Original Quality)_analysis.json",
    "projection": "homography",
    "gate_spacing_m": 14.0,
    "camera_pitch_deg": 10.0,
    "p90_speed_kmh": 166155.11737779187,
    "median_speed_kmh": 1710.647076567101,
    "raw_correction_factor": 3021.0021341416705,
    "auto_applied": false,
    "unable_to_calibrate": true,
    "reason": "correction_exceeds_cap",
    "n_dynamic_frames": 463
  },
  {
    "video_id": "2911",
    "analysis_json": "/Users/quan/Documents/personal/Stanford application project/artifacts/regression_20260214/new_model/2911_1765738746(Video in Original Quality)_analysis.json",
    "projection": "homography",
    "gate_spacing_m": 14.0,
    "camera_pitch_deg": 20.0,
    "p90_speed_kmh": 166155.11737779187,
    "median_speed_kmh": 1710.647076567101,
    "raw_correction_factor": 3021.0021341416705,
    "auto_applied": false,
    "unable_to_calibrate": true,
    "reason": "correction_exceeds_cap",
    "n_dynamic_frames": 463
  },
  {
    "video_id": "2911",
    "analysis_json": "/Users/quan/Documents/personal/Stanford application project/artifacts/regression_20260214/new_model/2911_1765738746(Video in Original Quality)_analysis.json",
    "projection": "homography",
    "gate_spacing_m": 14.0,
    "camera_pitch_deg": 30.0,
    "p90_speed_kmh": 166155.11737779187,
    "median_speed_kmh": 1710.647076567101,
    "raw_correction_factor": 3021.0021341416705,
    "auto_applied": false,
    "unable_to_calibrate": true,
    "reason": "correction_exceeds_cap",
    "n_dynamic_frames": 463
  }
]